MANIFEST.in
Makefile
README.rst
runtests.py
setup.py
branding/__init__.py
branding/middleware.py
branding/models.py
branding/settings.py
branding/tests/__init__.py
branding/tests/models.py
branding/tests/tests.py
django_branding.egg-info/PKG-INFO
django_branding.egg-info/SOURCES.txt
django_branding.egg-info/dependency_links.txt
django_branding.egg-info/not-zip-safe
django_branding.egg-info/requires.txt
django_branding.egg-info/top_level.txt