Metadata-Version: 1.1
Name: django-branding
Version: 0.0.6
Summary: Add branding headers to you response
Home-page: http://github.com/Lispython/django-branding
Author: Alexandr Lispython
Author-email: alex@dzone.me
License: UNKNOWN
Platform: UNKNOWN
Classifier: Framework :: Django
Classifier: Intended Audience :: Developers
Classifier: Intended Audience :: System Administrators
Classifier: Operating System :: OS Independent
Classifier: Topic :: Software Development
